{
    "font-normal": "JetBrainsMono-Regular.ttf",
    "font-bold": "JetBrainsMono-Bold.ttf",
    "font-italic": "JetBrainsMono-BoldItalic.ttf",
    "font-bold-italic": "JetBrainsMono-Italic.ttf",
    "font-size": 19,
    "width-margin": 5,
    "height-margin": 5,
    "spacing": 1,
    "background-color": [
        255,
        255,
        255
    ],
    "source-code": [
        "    [AOI=method_signature] public static int [AOI=method_identifier]lengthOfLastWord[/AOI][AOI=method_argument_declaration](String text)[/AOI][/AOI] {",
        "        int length = 0;",
        "        boolean isLastWord = false;",
        "        [AOI=for][AOI=for_head] for (int i = [AOI=arithmetic_expression][AOI=method_call]text.[AOI=method_call_identifier]length[/AOI][AOI=method_arguments]()[/AOI][/AOI] - 1[/AOI]; i >= 0; i--)[/AOI][AOI=for_body] {",
        "            char c = [AOI=method_call]text.[AOI=method_call_identifier]charAt[/AOI][AOI=method_arguments](i)[/AOI][/AOI];",
        "            [AOI=if][AOI=if_head] if ((c >= 'a' && c <= 'z') || (c >= 'A' && c <= 'Z'))[/AOI][AOI=if_body] {",
        "                isLastWord = true;",
        "                length++;",
        "            } [/AOI][/AOI][AOI=else][AOI=else_head] else [/AOI][AOI=else_body] {",
        "                [AOI=if][AOI=if_head] if (isLastWord) [/AOI][AOI=if_body]{",
        "                    break;",
        "                }[/AOI][/AOI]",
        "            }[/AOI][/AOI]",
        "        }[/AOI][/AOI]",
        "",
        "        return length;",
        "    }"
    ]
}
