{
    "font-normal": "JetBrainsMono-Regular.ttf",
    "font-bold": "JetBrainsMono-Bold.ttf",
    "font-italic": "JetBrainsMono-BoldItalic.ttf",
    "font-bold-italic": "JetBrainsMono-Italic.ttf",
    "font-size": 19,
    "width-margin": 5,
    "height-margin": 5,
    "spacing": 1,
    "background-color": [
        255,
        255,
        255
    ],
    "source-code": [
        "    [AOI=method_signature]public static int [AOI=method_identifier]binomialCoefficient[/AOI][AOI=method_argument_declaration](int n, int k)[/AOI][/AOI] {",
        "        int res = 1;",
        "",
        "        [AOI=if][AOI=if_head]if (k > [AOI=arithmetic_expression]n - k[/AOI])[/AOI][AOI=if_body]",
        "            [AOI=arithmetic_expression]k = [AOI=arithmetic_expression]n - k[/AOI];[/AOI][/AOI][/AOI]",
        "",
        "        [AOI=for][AOI=for_head]for (int i = 0; i < k; ++i)[/AOI][AOI=for_body]{",
        "            [AOI=arithmetic_expression]res *= (n - i);[/AOI]",
        "            [AOI=arithmetic_expression]res /= (i + 1);[/AOI]",
        "        }[/AOI][/AOI]",
        "        return res;",
        "    }"
    ]
}
